javadepsmanager/__init__.py
javadepsmanager/command_line.py
Java_Dependency_Manager-1.1.2.dist-info/LICENSE
Java_Dependency_Manager-1.1.2.dist-info/METADATA
Java_Dependency_Manager-1.1.2.dist-info/WHEEL
Java_Dependency_Manager-1.1.2.dist-info/entry_points.txt
Java_Dependency_Manager-1.1.2.dist-info/top_level.txt
Java_Dependency_Manager-1.1.2.dist-info/RECORD
