Metadata-Version: 2.1
Name: Java-Dependency-Manager
Version: 1.1.2
Summary: Generates Dependency tree for any java project also compares dependencies between two versions, use jdm in commandline to use this tool
Home-page: https://github.com/Nagaraju6242/javadepsmanager
Author: Repala Nagaraju
Author-email: nagarajrepala@gmail.com
License: MIT
Project-URL: Source Code, https://github.com/Nagaraju6242/javadepsmanager
Project-URL: Tracker, https://github.com/Nagaraju6242/javadepsmanager/issues
License-File: LICENSE
Requires-Dist: requests (==2.31.0)
